{
  "fixtureId": "roster-cb-oregon-state-partial",
  "screenKind": "roster_by_position",
  "game": "College Football 25",
  "partial": true,
  "notes": [],
  "navigation": {
    "teamCycle": "L2",
    "positionCycle": "R2",
    "selectedTeam": "OREGON STATE",
    "selectedPosition": "CB"
  },
  "teamContext": {
    "name": "Oregon State Beavers",
    "conference": "BIG TEN",
    "overallRating": 81,
    "offensiveRating": 81,
    "defensiveRating": 81
  },
  "regions": {
    "table": { "x": 0.02, "y": 0.2, "w": 0.53, "h": 0.68 },
    "detailPanel": { "x": 0.55, "y": 0.18, "w": 0.43, "h": 0.72 }
  },
  "table": {
    "columns": [
      { "key": "name", "header": "NAME", "kind": "text" },
      { "key": "year", "header": "YEAR", "kind": "text" },
      { "key": "position", "header": "POS", "kind": "text" },
      { "key": "overall", "header": "OVR", "kind": "number", "sortActive": true }
    ],
    "visibleRowCount": 10,
    "focusedRowIndex": 4,
    "hasMoreRows": true,
    "hasHorizontalScroll": true
  },
  "detailPanel": { "fields": ["fullName", "position", "overall"] },
  "imageFile": "roster-cb-oregon-state.partial.jpg"
}
